mosparo_django/__init__.py
mosparo_django/apps.py
mosparo_django/config.py
mosparo_django/fields.py
mosparo_django/forms.py
mosparo_django/widgets.py
mosparo_django/templates/mosparo/box.html
mosparo_django-1.0.7.dist-info/licenses/LICENSE
mosparo_django-1.0.7.dist-info/METADATA
mosparo_django-1.0.7.dist-info/WHEEL
mosparo_django-1.0.7.dist-info/top_level.txt
mosparo_django-1.0.7.dist-info/RECORD
