Metadata-Version: 2.4
Name: mosparo-django
Version: 1.0.7
Summary: A Django app to integrate mosparo into your forms.
Author-email: mosparo Core Developers <info@mosparo.io>
License-Expression: MIT
Project-URL: GitHub, https://github.com/mosparo/django-integration
Project-URL: Website, https://mosparo.io
Keywords: accessibility,app,captcha,django,mosparo,spam-protection
Classifier: Development Status :: 5 - Production/Stable
Classifier: Environment :: Web Environment
Classifier: Framework :: Django :: 3.2
Classifier: Framework :: Django :: 4
Classifier: Framework :: Django :: 4.2
Classifier: Framework :: Django :: 5.0
Classifier: Framework :: Django :: 5.1
Classifier: Framework :: Django :: 5.2
Classifier: Intended Audience :: Developers
Classifier: Operating System :: OS Independent
Classifier: Programming Language :: Python :: 3 :: Only
Classifier: Programming Language :: Python :: 3.6
Classifier: Programming Language :: Python :: 3.7
Classifier: Programming Language :: Python :: 3.8
Classifier: Programming Language :: Python :: 3.9
Classifier: Programming Language :: Python :: 3.10
Classifier: Programming Language :: Python :: 3.11
Classifier: Programming Language :: Python :: 3.12
Classifier: Programming Language :: Python :: 3.13
Classifier: Programming Language :: Python :: 3.14
Classifier: Topic :: Internet
Classifier: Topic :: Internet :: WWW/HTTP
Requires-Python: >=3.6
License-File: LICENSE
Requires-Dist: django>=3.2
Requires-Dist: mosparo-api-client>=1.1
Provides-Extra: dev
Requires-Dist: pytest-django; extra == "dev"
Requires-Dist: pytest-runner; extra == "dev"
Requires-Dist: requests-mock; extra == "dev"
Dynamic: license-file
